{
  "parent": "minecraft:story/upgrade_tools",
  "criteria": {
    "iron_pickaxe": {
      "conditions": {
        "items": [
          {
            "items": "minecraft:iron_pickaxe"
          }
        ]
      },
      "trigger": "minecraft:inventory_changed"
    },
    "iron_axe": {
      "conditions": {
        "items": [
          {
            "items": "minecraft:iron_axe"
          }
        ]
      },
      "trigger": "minecraft:inventory_changed"
    },
    "iron_hoe": {
      "conditions": {
        "items": [
          {
            "items": "minecraft:iron_hoe"
          }
        ]
      },
      "trigger": "minecraft:inventory_changed"
    },
    "iron_shovel": {
      "conditions": {
        "items": [
          {
            "items": "minecraft:iron_shovel"
          }
        ]
      },
      "trigger": "minecraft:inventory_changed"
    },
    "iron_sword": {
      "conditions": {
        "items": [
          {
            "items": "minecraft:iron_sword"
          }
        ]
      },
      "trigger": "minecraft:inventory_changed"
    },
    "iron_spear": {
      "conditions": {
        "items": [
          {
            "items": "minecraft:iron_spear"
          }
        ]
      },
      "trigger": "minecraft:inventory_changed"
    }
  },
  "display": {
    "description": {
      "translate": "content_lock:advancement.iron_tools.description"
    },
    "icon": {
      "count": 1,
      "id": "minecraft:iron_pickaxe"
    },
    "title": {
      "translate": "content_lock:advancement.iron_tools.title"
    }
  },
  "requirements": [
    [
      "iron_pickaxe",
      "iron_axe",
      "iron_hoe",
      "iron_shovel",
      "iron_sword",
      "iron_spear"
    ]
  ],
  "rewards": {
    "loot": [
        "content_lock:advancements/1_bottle"
    ]
  },
  "sends_telemetry_event": true
}