{
  "type": "minecraft:block",
  "pools": [
    {
      "bonus_rolls": 0,
      "entries": [
        {
          "type": "minecraft:alternatives",
          "children": [
            {
              "type": "minecraft:item",
              "functions": [
                {
                  "function": "minecraft:copy_components",
                  "include": [
                    "minecraft:bees"
                  ],
                  "source": "block_entity"
                },
                {
                  "block": "minecraft:bee_nest",
                  "function": "minecraft:copy_state",
                  "properties": [
                    "honey_level"
                  ]
                }
              ],
              "conditions": [
                {
                  "condition": "minecraft:match_tool",
                  "predicate": {
                    "predicates": {
                      "minecraft:enchantments": [
                        {
                          "enchantments": "minecraft:silk_touch",
                          "levels": {
                            "min": 1
                          }
                        }
                      ]
                    }
                  }
                }
              ],          
              "name": "minecraft:bee_nest"
            },
            {
              "type": "minecraft:item",
              "conditions": [
                {
                  "condition": "minecraft:survives_explosion"
                }
              ],
              "name": "minecraft:honeycomb",
              "functions": [
                {
                  "function": "minecraft:set_count",
                  "count": {
                    "min": 4,
                    "max": 7,
                    "type": "minecraft:uniform"
                  }
                }
              ]
            }
          ]
        }
      ],
      "rolls": 1
    }
  ],
  "random_sequence": "minecraft:blocks/bee_nest"
}